allegro_api/__init__.py
allegro_api/base.py
allegro_api/client.py
allegro_api/exceptions.py
allegro_api/auth/__init__.py
allegro_api/auth/oauth.py
allegro_api/resources/__init__.py
allegro_api/resources/advanced_offers.py
allegro_api/resources/auctions.py
allegro_api/resources/base.py
allegro_api/resources/billing.py
allegro_api/resources/categories.py
allegro_api/resources/customer_service.py
allegro_api/resources/fulfillment.py
allegro_api/resources/misc.py
allegro_api/resources/offers.py
allegro_api/resources/orders.py
allegro_api/resources/payments.py
allegro_api/resources/products.py
allegro_api/resources/promotions.py
allegro_api/resources/user.py
allegro_api-0.1.0.dist-info/LICENSE
allegro_api-0.1.0.dist-info/METADATA
allegro_api-0.1.0.dist-info/WHEEL
allegro_api-0.1.0.dist-info/top_level.txt
allegro_api-0.1.0.dist-info/RECORD
