Metadata-Version: 2.1
Name: allegro-api
Version: 0.1.0
Summary: Python client library for Allegro REST API with 100% API coverage
Author-email: Allegro API Python Contributors <marek.sybilak@neogento.com>
Maintainer-email: Marek Sybilak <marek.sybilak@neogento.com>
License: MIT
Project-URL: Homepage, https://github.com/yourusername/allegro-api-python
Project-URL: Bug Tracker, https://github.com/yourusername/allegro-api-python/issues
Project-URL: Documentation, https://allegro-api-python.readthedocs.io
Project-URL: Source Code, https://github.com/yourusername/allegro-api-python
Project-URL: Changelog, https://github.com/yourusername/allegro-api-python/blob/main/CHANGELOG.md
Keywords: allegro,api,e-commerce,marketplace,poland,rest-api,oauth2,allegro-pl,ecommerce-api
Classifier: Development Status :: 4 - Beta
Classifier: Intended Audience :: Developers
Classifier: Operating System :: OS Independent
Classifier: Programming Language :: Python :: 3
Classifier: Programming Language :: Python :: 3.7
Classifier: Programming Language :: Python :: 3.8
Classifier: Programming Language :: Python :: 3.9
Classifier: Programming Language :: Python :: 3.10
Classifier: Programming Language :: Python :: 3.11
Classifier: Programming Language :: Python :: 3.12
Classifier: Topic :: Software Development :: Libraries :: Python Modules
Classifier: Topic :: Internet :: WWW/HTTP
Classifier: Topic :: Office/Business
Classifier: Natural Language :: English
Classifier: Natural Language :: Polish
Requires-Python: >=3.7
License-File: LICENSE
Requires-Dist: requests>=2.28.0
Requires-Dist: requests-oauthlib>=1.3.0
Provides-Extra: dev
Requires-Dist: pytest>=7.0.0; extra == "dev"
Requires-Dist: pytest-cov>=4.0.0; extra == "dev"
Requires-Dist: pytest-mock>=3.10.0; extra == "dev"
Requires-Dist: black>=23.0.0; extra == "dev"
Requires-Dist: flake8>=6.0.0; extra == "dev"
Requires-Dist: mypy>=1.0.0; extra == "dev"
Requires-Dist: types-requests>=2.28.0; extra == "dev"
Provides-Extra: docs
Requires-Dist: sphinx>=5.0.0; extra == "docs"
Requires-Dist: sphinx-rtd-theme>=1.0.0; extra == "docs"
